monica/__init__.py
monica/version.py
monica_client-1.0.0a1.dist-info/LICENSE
monica_client-1.0.0a1.dist-info/METADATA
monica_client-1.0.0a1.dist-info/WHEEL
monica_client-1.0.0a1.dist-info/top_level.txt
monica_client-1.0.0a1.dist-info/RECORD
