Metadata-Version: 2.1
Name: monica-client
Version: 1.0.0a1
Summary: Client to connect to Monica CRM API
Home-page: https://github.com/tmbo/monica-client
Author: Tom Bocklisch
Author-email: tombocklisch@gmail.com
Maintainer: Tom Bocklisch
Maintainer-email: tombocklisch@gmail.com
License: Apache 2.0
Download-URL: https://github.com/tmbo/monica-client/archive/1.0.0a1.tar.gz
Project-URL: Bug Reports, https://github.com/tmbo/monica-client/issues
Project-URL: Source, https://github.com/tmbo/monica-client
Keywords: monica,crm,api
Platform: UNKNOWN
Classifier: Development Status :: 4 - Beta
Classifier: Intended Audience :: Developers
Classifier: License :: OSI Approved :: Apache Software License
Classifier: Programming Language :: Python
Classifier: Programming Language :: Python :: 3.5
Classifier: Programming Language :: Python :: 3.6
Classifier: Topic :: Software Development :: Libraries
Requires-Dist: requests
